Metadata-Version: 2.4
Name: dspy-async
Version: 2.6.17
Summary: DSPy
Author-email: Omar Khattab <okhattab@stanford.edu>, Will Swift <will@afterdarkstudio.dev>
License: MIT License
Project-URL: homepage, https://github.com/stanfordnlp/dspy
Classifier: Development Status :: 3 - Alpha
Classifier: Intended Audience :: Science/Research
Classifier: License :: OSI Approved :: MIT License
Classifier: Operating System :: POSIX :: Linux
Classifier: Programming Language :: Python :: 3
Requires-Python: <3.13,>=3.9
License-File: LICENSE
Requires-Dist: backoff>=2.2
Requires-Dist: joblib~=1.3
Requires-Dist: openai<=1.61.0,>=0.28.1
Requires-Dist: pandas>=2.1.1
Requires-Dist: regex>=2023.10.3
Requires-Dist: ujson>=5.8.0
Requires-Dist: tqdm>=4.66.1
Requires-Dist: datasets>=2.14.6
Requires-Dist: requests>=2.31.0
Requires-Dist: optuna>=3.4.0
Requires-Dist: pydantic>=2.0
Requires-Dist: magicattr>=0.1.6
Requires-Dist: litellm>=1.60.3
Requires-Dist: diskcache>=5.6.0
Requires-Dist: json-repair>=0.30.0
Requires-Dist: tenacity>=8.2.3
Requires-Dist: anyio
Requires-Dist: asyncer==0.0.8
Requires-Dist: cachetools>=5.5.0
Requires-Dist: cloudpickle>=3.0.0
Requires-Dist: rich>=13.7.1
Requires-Dist: numpy<2.2,>=1.26.0; python_version == "3.9"
Requires-Dist: numpy>=1.26.0; python_version >= "3.10"
Provides-Extra: anthropic
Requires-Dist: anthropic<1.0.0,>=0.18.0; extra == "anthropic"
Provides-Extra: chromadb
Requires-Dist: chromadb~=0.4.14; extra == "chromadb"
Provides-Extra: lancedb
Requires-Dist: lancedb>=0.19.0; extra == "lancedb"
Provides-Extra: qdrant
Requires-Dist: qdrant-client>=1.11.1; extra == "qdrant"
Requires-Dist: fastembed>=0.2.0; extra == "qdrant"
Provides-Extra: marqo
Requires-Dist: marqo; extra == "marqo"
Provides-Extra: epsilla
Requires-Dist: pyepsilla~=0.3.7; extra == "epsilla"
Provides-Extra: pinecone
Requires-Dist: pinecone-client~=2.2.4; extra == "pinecone"
Provides-Extra: weaviate
Requires-Dist: weaviate-client~=4.5.4; extra == "weaviate"
Provides-Extra: milvus
Requires-Dist: pymilvus~=2.3.7; extra == "milvus"
Provides-Extra: aws
Requires-Dist: boto3~=1.34.78; extra == "aws"
Provides-Extra: docs
Requires-Dist: sphinx>=4.3.0; extra == "docs"
Requires-Dist: furo>=2023.3.27; extra == "docs"
Requires-Dist: docutils<0.17; extra == "docs"
Requires-Dist: m2r2; extra == "docs"
Requires-Dist: myst-parser; extra == "docs"
Requires-Dist: myst-nb; extra == "docs"
Requires-Dist: sphinx-autobuild; extra == "docs"
Requires-Dist: sphinx_rtd_theme; extra == "docs"
Requires-Dist: autodoc_pydantic; extra == "docs"
Requires-Dist: sphinx-reredirects>=0.1.2; extra == "docs"
Requires-Dist: sphinx-automodapi==0.16.0; extra == "docs"
Provides-Extra: dev
Requires-Dist: pytest>=6.2.5; extra == "dev"
Provides-Extra: fastembed
Requires-Dist: fastembed>=0.2.0; extra == "fastembed"
Dynamic: license-file
